README.md
sqlagen/.DS_Store
sqlagen/__init__.py
sqlagen/cli/__init__.py
sqlagen/generator/.DS_Store
sqlagen/generator/__init__.py
sqlagen/generator/model/__init__.py
sqlagen/generator/model/generator.py
sqlagen/generator/model/models.py
sqlagen/generator/model/utils.py
sqlagen/generator/schema/__init__.py
sqlagen/generator/schema/generator.py
sqlagen/generator/schema/models.py
sqlagen/generator/schema/utils.py
sqlagen/py.typed
sqlagen-0.1.3.dist-info/LICENSE
sqlagen-0.1.3.dist-info/METADATA
sqlagen-0.1.3.dist-info/WHEEL
sqlagen-0.1.3.dist-info/entry_points.txt
sqlagen-0.1.3.dist-info/RECORD
