Metadata-Version: 2.1
Name: sqlagen
Version: 0.1.3
Summary: 
Home-page: https://github.com/maacck/sqlagen
Keywords: pydantic,sqlalchemy
Author: maacck
Author-email: c.mai@madainchina.com
Requires-Python: >=3.10,<4.0
Classifier: Programming Language :: Python :: 3
Classifier: Programming Language :: Python :: 3.10
Classifier: Programming Language :: Python :: 3.11
Classifier: Programming Language :: Python :: 3.12
Requires-Dist: inflect (>=4.0.0,<5.0.0)
Requires-Dist: pydantic (>=2.0.0,<3.0.0)
Requires-Dist: sqlalchemy (>=2.0.0,<3.0.0)
Requires-Dist: typer (>=0.12.3,<0.13.0)
Project-URL: Repository, https://github.com/maacck/sqlagen
